handwrite/__init__.py
handwrite/cli.py
handwrite/default.json
handwrite/pngtosvg.py
handwrite/sheettopng.py
handwrite/svgtottf.py
tests/__init__.py
tests/test_cli.py
tests/test_pngtosvg.py
tests/test_sheettopng.py
tests/test_svgtottf.py
handwrite-0.3.1.dist-info/LICENSE
handwrite-0.3.1.dist-info/METADATA
handwrite-0.3.1.dist-info/WHEEL
handwrite-0.3.1.dist-info/entry_points.txt
handwrite-0.3.1.dist-info/top_level.txt
handwrite-0.3.1.dist-info/RECORD
