Metadata-Version: 2.1
Name: handwrite
Version: 0.3.1
Summary: Convert text to custom handwriting
Home-page: https://github.com/builtree/handwrite
Author: Yash Lamba, Saksham Arora, Aryan Gupta
Author-email: yashlamba2000@gmail.com, sakshamarora1001@gmail.com, aryangupta973@gmail.com
License: UNKNOWN
Platform: UNKNOWN
Classifier: Programming Language :: Python :: 3
Classifier: License :: OSI Approved :: MIT License
Classifier: Operating System :: OS Independent
Requires-Python: >=3.7
Provides-Extra: dev
